nessaid_readline/__init__.py
nessaid_readline/async_readline.py
nessaid_readline/key.py
nessaid_readline/readkey.py
nessaid_readline/readline.py
nessaid_readline-0.4.0.dist-info/LICENSE
nessaid_readline-0.4.0.dist-info/METADATA
nessaid_readline-0.4.0.dist-info/WHEEL
nessaid_readline-0.4.0.dist-info/top_level.txt
nessaid_readline-0.4.0.dist-info/RECORD
